odoo/addons/l10n_fi_sale_refund_payment_reference/LICENSE
odoo/addons/l10n_fi_sale_refund_payment_reference/README.rst
odoo/addons/l10n_fi_sale_refund_payment_reference/__init__.py
odoo/addons/l10n_fi_sale_refund_payment_reference/__manifest__.py
odoo/addons/l10n_fi_sale_refund_payment_reference/i18n/l10n_fi_sale_refund_payment_reference.pot
odoo/addons/l10n_fi_sale_refund_payment_reference/models/__init__.py
odoo/addons/l10n_fi_sale_refund_payment_reference/models/account_move.py
odoo/addons/l10n_fi_sale_refund_payment_reference/readme/CONTRIBUTORS.md
odoo/addons/l10n_fi_sale_refund_payment_reference/readme/DESCRIPTION.md
odoo/addons/l10n_fi_sale_refund_payment_reference/readme/HISTORY.md
odoo/addons/l10n_fi_sale_refund_payment_reference/readme/USAGE.md
odoo/addons/l10n_fi_sale_refund_payment_reference/static/description/icon.png
odoo/addons/l10n_fi_sale_refund_payment_reference/static/description/index.html
odoo/addons/l10n_fi_sale_refund_payment_reference/tests/__init__.py
odoo/addons/l10n_fi_sale_refund_payment_reference/tests/test_refund_reference.py
odoo_addon_l10n_fi_sale_refund_payment_reference-19.0.1.0.0.2.dist-info/METADATA
odoo_addon_l10n_fi_sale_refund_payment_reference-19.0.1.0.0.2.dist-info/WHEEL
odoo_addon_l10n_fi_sale_refund_payment_reference-19.0.1.0.0.2.dist-info/top_level.txt
odoo_addon_l10n_fi_sale_refund_payment_reference-19.0.1.0.0.2.dist-info/RECORD
