Metadata-Version: 2.1
Name: odoo-addon-l10n_fi_sale_refund_payment_reference
Version: 19.0.1.0.0.2
Requires-Dist: odoo==19.0.*
Summary: Automatically generate payment references for sale refunds
Home-page: https://github.com/OCA/l10n-finland
License: AGPL-3
Author: Avoin.Systems, Odoo Community Association (OCA)
Author-email: support@odoo-community.org
Classifier: Programming Language :: Python
Classifier: Framework :: Odoo
Classifier: Framework :: Odoo :: 19.0
Classifier: License :: OSI Approved :: GNU Affero General Public License v3
